{"name": "CTA_202503", "kpi": {"kpi_2y": {"Net_Profit": "87.042w", "Max_Drawdown": "5.745w", "Ann_Sharpe": "2.982", "Daily_Std": "0.961w"}, "kpi_6m": {"Net_Profit": "28.252w", "Max_Drawdown": "5.642w", "Ann_Sharpe": "3.869", "Daily_Std": "1.022w"}}, "children": [{"name": "CTA_TS_HTOR_V2", "kpi": {"kpi_2y": {"Net_Profit": "94.913w", "Max_Drawdown": "5.324w", "Ann_Sharpe": "3.397", "Daily_Std": "0.920w"}, "kpi_6m": {"Net_Profit": "39.632w", "Max_Drawdown": "5.324w", "Ann_Sharpe": "4.325", "Daily_Std": "1.282w"}}, "children": [], "ratio": 33.0, "_drillable": true}, {"name": "CTA_TS_MTOR_V2", "kpi": {"kpi_2y": {"Net_Profit": "51.343w", "Max_Drawdown": "10.846w", "Ann_Sharpe": "1.366", "Daily_Std": "1.238w"}, "kpi_6m": {"Net_Profit": "26.736w", "Max_Drawdown": "7.164w", "Ann_Sharpe": "2.771", "Daily_Std": "1.350w"}}, "children": [], "ratio": 10.42105263, "_drillable": true}, {"name": "CTA_TS_LTOR", "kpi": {"kpi_2y": {"Net_Profit": "43.332w", "Max_Drawdown": "8.038w", "Ann_Sharpe": "1.504", "Daily_Std": "0.949w"}, "kpi_6m": {"Net_Profit": "13.615w", "Max_Drawdown": "7.362w", "Ann_Sharpe": "1.767", "Daily_Std": "1.078w"}}, "children": [], "ratio": 18.33333333, "_drillable": true}, {"name": "CTA_HS_LTOR", "kpi": {"kpi_2y": {"Net_Profit": "37.444w", "Max_Drawdown": "7.126w", "Ann_Sharpe": "1.756", "Daily_Std": "0.702w"}, "kpi_6m": {"Net_Profit": "12.273w", "Max_Drawdown": "2.178w", "Ann_Sharpe": "3.056", "Daily_Std": "0.562w"}}, "children": [], "ratio": 38.82352941, "_drillable": true}, {"name": "CTA_TS_MTOR_V2_Risk_V2", "kpi": {"kpi_2y": {"Net_Profit": "67.407w", "Max_Drawdown": "8.065w", "Ann_Sharpe": "2.755", "Daily_Std": "0.806w"}, "kpi_6m": {"Net_Profit": "22.457w", "Max_Drawdown": "7.081w", "Ann_Sharpe": "3.374", "Daily_Std": "0.931w"}}, "children": [], "ratio": 7.642105263}, {"name": "CTA_TS_LTOR_Risk_V2", "kpi": {"kpi_2y": {"Net_Profit": "35.191w", "Max_Drawdown": "4.276w", "Ann_Sharpe": "1.890", "Daily_Std": "0.613w"}, "kpi_6m": {"Net_Profit": "9.048w", "Max_Drawdown": "4.276w", "Ann_Sharpe": "1.998", "Daily_Std": "0.634w"}}, "children": [], "ratio": 13.44444444}], "ratio": 43.99829999999999}