{"name": "pyelf_21ENetLong_adx_day_2025wf", "kpi": {"kpi_2y": {"Net_Profit": "194.111w", "Max_Drawdown": "27.797w", "Ann_Sharpe": "2.230", "Daily_Std": "2.862w"}, "kpi_6m": {"Net_Profit": "34.789w", "Max_Drawdown": "27.797w", "Ann_Sharpe": "1.392", "Daily_Std": "3.497w"}}, "children": [{"name": "pyelf_21ENet6MDiffYP5_adx_day_2025wf", "kpi": {"kpi_2y": {"Net_Profit": "198.086w", "Max_Drawdown": "24.065w", "Ann_Sharpe": "2.344", "Daily_Std": "2.778w"}, "kpi_6m": {"Net_Profit": "41.428w", "Max_Drawdown": "24.065w", "Ann_Sharpe": "1.736", "Daily_Std": "3.338w"}}, "children": [], "ratio": 34.0}, {"name": "pyelf_21ENet5MDiffYP3_adx_day_2025wf", "kpi": {"kpi_2y": {"Net_Profit": "188.291w", "Max_Drawdown": "38.460w", "Ann_Sharpe": "1.930", "Daily_Std": "3.207w"}, "kpi_6m": {"Net_Profit": "37.053w", "Max_Drawdown": "38.460w", "Ann_Sharpe": "1.215", "Daily_Std": "4.267w"}}, "children": [], "ratio": 34.0}, {"name": "pyelf_21ENet5MDiffYP5_adx_day_2025wf", "kpi": {"kpi_2y": {"Net_Profit": "208.226w", "Max_Drawdown": "25.727w", "Ann_Sharpe": "2.325", "Daily_Std": "2.944w"}, "kpi_6m": {"Net_Profit": "39.568w", "Max_Drawdown": "25.727w", "Ann_Sharpe": "1.653", "Daily_Std": "3.349w"}}, "children": [], "ratio": 32.0}], "ratio": 33.3}