{"name": "pyelf_21ENetStock_DayDiff_2024wf", "kpi": {"kpi_2y": {"Net_Profit": "21.209w", "Max_Drawdown": "32.420w", "Ann_Sharpe": "0.464", "Daily_Std": "1.503w"}, "kpi_6m": {"Net_Profit": "-8.660w", "Max_Drawdown": "19.473w", "Ann_Sharpe": "-0.600", "Daily_Std": "2.003w"}}, "children": [{"name": "pyelf_21ENetStock10WholeMonthDiff_11minYP13Slope_day_2024", "kpi": {"kpi_2y": {"Net_Profit": "25.056w", "Max_Drawdown": "24.366w", "Ann_Sharpe": "0.556", "Daily_Std": "1.482w"}, "kpi_6m": {"Net_Profit": "-5.064w", "Max_Drawdown": "24.366w", "Ann_Sharpe": "-0.332", "Daily_Std": "2.119w"}}, "children": [], "ratio": 21.16836584}, {"name": "pyelf_21ENetStock10WholeMonthDiff_11minYP13SR_day_2024", "kpi": {"kpi_2y": {"Net_Profit": "43.762w", "Max_Drawdown": "29.746w", "Ann_Sharpe": "0.698", "Daily_Std": "2.061w"}, "kpi_6m": {"Net_Profit": "-13.496w", "Max_Drawdown": "27.204w", "Ann_Sharpe": "-0.862", "Daily_Std": "2.173w"}}, "children": [], "ratio": 10.7310883}, {"name": "pyelf_21ENetStock10WholeMonthDiff_13minYP13Slope_day_2024", "kpi": {"kpi_2y": {"Net_Profit": "37.813w", "Max_Drawdown": "39.551w", "Ann_Sharpe": "0.685", "Daily_Std": "1.815w"}, "kpi_6m": {"Net_Profit": "-5.612w", "Max_Drawdown": "19.225w", "Ann_Sharpe": "-0.365", "Daily_Std": "2.131w"}}, "children": [], "ratio": 12.51822406}, {"name": "pyelf_21ENetStock10WholeMonthDiff_13minYP13SR_day_2024", "kpi": {"kpi_2y": {"Net_Profit": "-1.424w", "Max_Drawdown": "45.713w", "Ann_Sharpe": "-0.026", "Daily_Std": "1.810w"}, "kpi_6m": {"Net_Profit": "-24.690w", "Max_Drawdown": "26.536w", "Ann_Sharpe": "-1.593", "Daily_Std": "2.149w"}}, "children": [], "ratio": 11.75679696}, {"name": "pyelf_21ENetStock10WholeMonthDiff_19minYP13Slope_day_2024", "kpi": {"kpi_2y": {"Net_Profit": "14.473w", "Max_Drawdown": "40.801w", "Ann_Sharpe": "0.293", "Daily_Std": "1.626w"}, "kpi_6m": {"Net_Profit": "-1.138w", "Max_Drawdown": "18.817w", "Ann_Sharpe": "-0.066", "Daily_Std": "2.388w"}}, "children": [], "ratio": 13.55270167}, {"name": "pyelf_21ENetStock10WholeMonthDiff_19minYP13SR_day_2024", "kpi": {"kpi_2y": {"Net_Profit": "17.479w", "Max_Drawdown": "37.224w", "Ann_Sharpe": "0.378", "Daily_Std": "1.518w"}, "kpi_6m": {"Net_Profit": "-2.940w", "Max_Drawdown": "18.437w", "Ann_Sharpe": "-0.191", "Daily_Std": "2.130w"}}, "children": [], "ratio": 15.98044941}, {"name": "pyelf_21ENetStock5WholeMonthDiff_19minYP3SR_day_2024", "kpi": {"kpi_2y": {"Net_Profit": "12.737w", "Max_Drawdown": "33.890w", "Ann_Sharpe": "0.269", "Daily_Std": "1.555w"}, "kpi_6m": {"Net_Profit": "-13.674w", "Max_Drawdown": "17.131w", "Ann_Sharpe": "-0.943", "Daily_Std": "2.011w"}}, "children": [], "ratio": 14.29237377}], "ratio": 5.078}