{"name": "AutoCTA_short_index_202503", "kpi": {"kpi_2y": {"Net_Profit": "73.952w", "Max_Drawdown": "7.224w", "Ann_Sharpe": "2.419", "Daily_Std": "1.003w"}, "kpi_6m": {"Net_Profit": "21.302w", "Max_Drawdown": "7.152w", "Ann_Sharpe": "2.327", "Daily_Std": "1.216w"}}, "children": [{"name": "RawSigSS-IterBKT-SS2223", "kpi": {"kpi_2y": {"Net_Profit": "13.633w", "Max_Drawdown": "2.753w", "Ann_Sharpe": "1.429", "Daily_Std": "0.313w"}, "kpi_6m": {"Net_Profit": "6.743w", "Max_Drawdown": "2.753w", "Ann_Sharpe": "2.391", "Daily_Std": "0.375w"}}, "children": [], "ratio": 66.38}, {"name": "RawSigSSRY_IterBKT_SS2024", "kpi": {"kpi_2y": {"Net_Profit": "64.609w", "Max_Drawdown": "7.709w", "Ann_Sharpe": "2.109", "Daily_Std": "1.005w"}, "kpi_6m": {"Net_Profit": "10.066w", "Max_Drawdown": "3.718w", "Ann_Sharpe": "1.551", "Daily_Std": "0.863w"}}, "children": [], "ratio": 15.02}, {"name": "RawSigSS_IterBKT_SS202409", "kpi": {"kpi_2y": {"Net_Profit": "44.253w", "Max_Drawdown": "3.914w", "Ann_Sharpe": "2.560", "Daily_Std": "0.567w"}, "kpi_6m": {"Net_Profit": "11.156w", "Max_Drawdown": "3.834w", "Ann_Sharpe": "2.154", "Daily_Std": "0.688w"}}, "children": [], "ratio": 77.13}, {"name": "RawSigSS_IterBKT_SS202409_SelectTop", "kpi": {"kpi_2y": {"Net_Profit": "53.879w", "Max_Drawdown": "5.469w", "Ann_Sharpe": "2.397", "Daily_Std": "0.737w"}, "kpi_6m": {"Net_Profit": "20.103w", "Max_Drawdown": "4.811w", "Ann_Sharpe": "2.812", "Daily_Std": "0.950w"}}, "children": [], "ratio": 34.79}, {"name": "RawSigSS_IterBKT_SS202409_VBigTpBigpTwp", "kpi": {"kpi_2y": {"Net_Profit": "31.221w", "Max_Drawdown": "4.684w", "Ann_Sharpe": "1.947", "Daily_Std": "0.526w"}, "kpi_6m": {"Net_Profit": "6.088w", "Max_Drawdown": "4.319w", "Ann_Sharpe": "1.452", "Daily_Std": "0.557w"}}, "children": [], "ratio": 17.4}], "ratio": 100.0}