{"name": "CTA_TS_MTOR_2025", "kpi": {"kpi_2y": {"Net_Profit": "79.904w", "Max_Drawdown": "10.170w", "Ann_Sharpe": "2.181", "Daily_Std": "1.199w"}, "kpi_6m": {"Net_Profit": "19.410w", "Max_Drawdown": "7.056w", "Ann_Sharpe": "2.171", "Daily_Std": "1.198w"}}, "children": [{"name": "YYMONTHDIFF_INTRADAY_DAY_BIGTP", "kpi": {"kpi_2y": {"Net_Profit": "30.608w", "Max_Drawdown": "3.773w", "Ann_Sharpe": "2.156", "Daily_Std": "0.465w"}, "kpi_6m": {"Net_Profit": "6.945w", "Max_Drawdown": "2.285w", "Ann_Sharpe": "1.973", "Daily_Std": "0.472w"}}, "children": [], "ratio": 92.34}, {"name": "YYMONTHDIFF_INTRADAY_DAY_BIGTPV2", "kpi": {"kpi_2y": {"Net_Profit": "47.384w", "Max_Drawdown": "7.635w", "Ann_Sharpe": "2.195", "Daily_Std": "0.707w"}, "kpi_6m": {"Net_Profit": "10.618w", "Max_Drawdown": "4.093w", "Ann_Sharpe": "1.870", "Daily_Std": "0.761w"}}, "children": [], "ratio": 25.64}, {"name": "YYMONTHDIFF_INTRADAY_DAY_NOEXREM", "kpi": {"kpi_2y": {"Net_Profit": "35.252w", "Max_Drawdown": "6.827w", "Ann_Sharpe": "1.705", "Daily_Std": "0.677w"}, "kpi_6m": {"Net_Profit": "10.426w", "Max_Drawdown": "3.712w", "Ann_Sharpe": "2.303", "Daily_Std": "0.607w"}}, "children": [], "ratio": 35.62945368}, {"name": "YYMONTHDIFF_INTRADAY_DAY_NOEXREMV2", "kpi": {"kpi_2y": {"Net_Profit": "70.974w", "Max_Drawdown": "8.980w", "Ann_Sharpe": "2.225", "Daily_Std": "1.044w"}, "kpi_6m": {"Net_Profit": "20.718w", "Max_Drawdown": "6.768w", "Ann_Sharpe": "2.642", "Daily_Std": "1.051w"}}, "children": [], "ratio": 11.04}, {"name": "YYMONTHDIFF_INTRADAY_DAY_BIGTPV1", "kpi": {"kpi_2y": {"Net_Profit": "36.376w", "Max_Drawdown": "3.647w", "Ann_Sharpe": "2.213", "Daily_Std": "0.538w"}, "kpi_6m": {"Net_Profit": "18.862w", "Max_Drawdown": "3.513w", "Ann_Sharpe": "3.461", "Daily_Std": "0.730w"}}, "children": [], "ratio": 31.19}, {"name": "YYMONTHDIFF_INTRADAY_DAY_NOEXREMV1", "kpi": {"kpi_2y": {"Net_Profit": "42.819w", "Max_Drawdown": "6.686w", "Ann_Sharpe": "1.949", "Daily_Std": "0.719w"}, "kpi_6m": {"Net_Profit": "13.126w", "Max_Drawdown": "4.607w", "Ann_Sharpe": "2.588", "Daily_Std": "0.680w"}}, "children": [], "ratio": 11.04}], "ratio": 94.0}