{"name": "CTA_TS_HTOR_V2", "kpi": {"kpi_2y": {"Net_Profit": "84.507w", "Max_Drawdown": "8.741w", "Ann_Sharpe": "2.748", "Daily_Std": "1.007w"}, "kpi_6m": {"Net_Profit": "27.462w", "Max_Drawdown": "8.741w", "Ann_Sharpe": "2.508", "Daily_Std": "1.443w"}}, "children": [{"name": "CTA_TS_HTOR", "kpi": {"kpi_2y": {"Net_Profit": "90.009w", "Max_Drawdown": "8.264w", "Ann_Sharpe": "2.860", "Daily_Std": "1.030w"}, "kpi_6m": {"Net_Profit": "24.449w", "Max_Drawdown": "8.264w", "Ann_Sharpe": "2.460", "Daily_Std": "1.309w"}}, "children": [], "ratio": 75.0, "_drillable": true}, {"name": "CTA_TS_HTOR_OPT_V2_TW", "kpi": {"kpi_2y": {"Net_Profit": "99.187w", "Max_Drawdown": "18.625w", "Ann_Sharpe": "2.508", "Daily_Std": "1.295w"}, "kpi_6m": {"Net_Profit": "8.490w", "Max_Drawdown": "18.625w", "Ann_Sharpe": "0.615", "Daily_Std": "1.819w"}}, "children": [], "ratio": 2.0}, {"name": "RawSigSS_IterBKT_Jin10ZX", "kpi": {"kpi_2y": {"Net_Profit": "60.852w", "Max_Drawdown": "8.333w", "Ann_Sharpe": "2.169", "Daily_Std": "0.919w"}, "kpi_6m": {"Net_Profit": "11.666w", "Max_Drawdown": "8.333w", "Ann_Sharpe": "1.518", "Daily_Std": "1.012w"}}, "children": [], "ratio": 7.0}, {"name": "RAWSIGSS_PATCH", "kpi": {}, "children": [], "ratio": 70.0, "_drillable": true}, {"name": "CTA_TS_HTOR_RISK_TW", "kpi": {"kpi_2y": {"Net_Profit": "91.561w", "Max_Drawdown": "5.582w", "Ann_Sharpe": "3.085", "Daily_Std": "0.972w"}, "kpi_6m": {"Net_Profit": "31.226w", "Max_Drawdown": "3.416w", "Ann_Sharpe": "4.040", "Daily_Std": "1.018w"}}, "children": [], "ratio": 16.0}], "ratio": 33.0}