{"name": "Deap_comm_2026_index", "kpi": {"kpi_2y": {"Net_Profit": "82.120w", "Max_Drawdown": "7.558w", "Ann_Sharpe": "3.033", "Daily_Std": "0.886w"}, "kpi_6m": {"Net_Profit": "19.931w", "Max_Drawdown": "7.558w", "Ann_Sharpe": "2.674", "Daily_Std": "1.025w"}}, "children": [{"name": "Deap_comm_daynight_combine_Equal", "kpi": {"kpi_2y": {"Net_Profit": "96.043w", "Max_Drawdown": "13.100w", "Ann_Sharpe": "2.546", "Daily_Std": "1.235w"}, "kpi_6m": {"Net_Profit": "28.955w", "Max_Drawdown": "9.464w", "Ann_Sharpe": "2.857", "Daily_Std": "1.393w"}}, "children": [], "ratio": 30.0}, {"name": "Deap_comm_daynight_combine_ML", "kpi": {"kpi_2y": {"Net_Profit": "91.298w", "Max_Drawdown": "23.364w", "Ann_Sharpe": "2.459", "Daily_Std": "1.215w"}, "kpi_6m": {"Net_Profit": "4.908w", "Max_Drawdown": "23.364w", "Ann_Sharpe": "0.330", "Daily_Std": "2.044w"}}, "children": [], "ratio": 0.0}, {"name": "Deap_comm_daynight_combine_MLpos", "kpi": {"kpi_2y": {"Net_Profit": "63.754w", "Max_Drawdown": "7.476w", "Ann_Sharpe": "2.638", "Daily_Std": "0.791w"}, "kpi_6m": {"Net_Profit": "13.929w", "Max_Drawdown": "5.750w", "Ann_Sharpe": "2.137", "Daily_Std": "0.896w"}}, "children": [], "ratio": 25.0}, {"name": "Deap_comm_daynight_combine_rSharpe", "kpi": {"kpi_2y": {"Net_Profit": "73.291w", "Max_Drawdown": "9.574w", "Ann_Sharpe": "2.476", "Daily_Std": "0.969w"}, "kpi_6m": {"Net_Profit": "24.979w", "Max_Drawdown": "7.202w", "Ann_Sharpe": "3.185", "Daily_Std": "1.078w"}}, "children": [], "ratio": 45.0}], "ratio": 8.0}