{"name": "Deap_comm_2026_index_opt", "kpi": {"kpi_2y": {"Net_Profit": "71.887w", "Max_Drawdown": "3.973w", "Ann_Sharpe": "3.093", "Daily_Std": "0.762w"}, "kpi_6m": {"Net_Profit": "18.525w", "Max_Drawdown": "3.945w", "Ann_Sharpe": "2.901", "Daily_Std": "0.870w"}}, "children": [{"name": "Deap_comm_daynight_combine_ML_opt", "kpi": {"kpi_2y": {"Net_Profit": "97.174w", "Max_Drawdown": "9.085w", "Ann_Sharpe": "3.625", "Daily_Std": "0.879w"}, "kpi_6m": {"Net_Profit": "11.636w", "Max_Drawdown": "9.085w", "Ann_Sharpe": "1.350", "Daily_Std": "1.175w"}}, "children": [], "ratio": 0.0}, {"name": "Deap_comm_daynight_combine_MLpos_opt", "kpi": {"kpi_2y": {"Net_Profit": "79.186w", "Max_Drawdown": "7.003w", "Ann_Sharpe": "3.319", "Daily_Std": "0.783w"}, "kpi_6m": {"Net_Profit": "21.001w", "Max_Drawdown": "4.685w", "Ann_Sharpe": "3.266", "Daily_Std": "0.876w"}}, "children": [], "ratio": 25.0}, {"name": "Deap_comm_daynight_combine_rSharpe_opt", "kpi": {"kpi_2y": {"Net_Profit": "67.930w", "Max_Drawdown": "8.770w", "Ann_Sharpe": "2.602", "Daily_Std": "0.856w"}, "kpi_6m": {"Net_Profit": "19.717w", "Max_Drawdown": "4.776w", "Ann_Sharpe": "3.203", "Daily_Std": "0.839w"}}, "children": [], "ratio": 45.0}, {"name": "Deap_comm_daynight_combine_Equal_opt", "kpi": {"kpi_2y": {"Net_Profit": "94.742w", "Max_Drawdown": "9.792w", "Ann_Sharpe": "2.877", "Daily_Std": "1.080w"}, "kpi_6m": {"Net_Profit": "25.001w", "Max_Drawdown": "5.309w", "Ann_Sharpe": "3.131", "Daily_Std": "1.088w"}}, "children": [], "ratio": 30.0}], "ratio": 39.0}