{"name": "Deap_comm_index_opt", "kpi": {"kpi_2y": {"Net_Profit": "58.152w", "Max_Drawdown": "6.034w", "Ann_Sharpe": "2.457", "Daily_Std": "0.778w"}, "kpi_6m": {"Net_Profit": "10.772w", "Max_Drawdown": "6.034w", "Ann_Sharpe": "1.941", "Daily_Std": "0.763w"}}, "children": [{"name": "Deap_comm_daynight_v2_opt", "kpi": {"kpi_2y": {"Net_Profit": "66.391w", "Max_Drawdown": "9.581w", "Ann_Sharpe": "2.393", "Daily_Std": "0.912w"}, "kpi_6m": {"Net_Profit": "14.737w", "Max_Drawdown": "9.581w", "Ann_Sharpe": "1.942", "Daily_Std": "1.043w"}}, "children": [], "ratio": 50.0}, {"name": "Deap_benchmark_v4_opt", "kpi": {"kpi_2y": {"Net_Profit": "71.087w", "Max_Drawdown": "13.208w", "Ann_Sharpe": "2.175", "Daily_Std": "1.074w"}, "kpi_6m": {"Net_Profit": "12.601w", "Max_Drawdown": "10.115w", "Ann_Sharpe": "1.294", "Daily_Std": "1.339w"}}, "children": [], "ratio": 10.0}, {"name": "Deap_benchmark_v4_ML_opt", "kpi": {"kpi_2y": {"Net_Profit": "74.459w", "Max_Drawdown": "6.393w", "Ann_Sharpe": "3.166", "Daily_Std": "0.773w"}, "kpi_6m": {"Net_Profit": "10.318w", "Max_Drawdown": "4.936w", "Ann_Sharpe": "1.758", "Daily_Std": "0.807w"}}, "children": [], "ratio": 10.0}, {"name": "Deap_benchmark_v5_ML_opt", "kpi": {"kpi_2y": {"Net_Profit": "84.368w", "Max_Drawdown": "7.480w", "Ann_Sharpe": "3.365", "Daily_Std": "0.824w"}, "kpi_6m": {"Net_Profit": "19.702w", "Max_Drawdown": "6.357w", "Ann_Sharpe": "2.904", "Daily_Std": "0.933w"}}, "children": [], "ratio": 10.0}, {"name": "Deap_benchmark_v4_ML_cs", "kpi": {"kpi_2y": {"Net_Profit": "78.787w", "Max_Drawdown": "7.534w", "Ann_Sharpe": "3.155", "Daily_Std": "0.821w"}, "kpi_6m": {"Net_Profit": "7.553w", "Max_Drawdown": "4.939w", "Ann_Sharpe": "1.238", "Daily_Std": "0.839w"}}, "children": [], "ratio": 10.0}, {"name": "Deap_benchmark_v5_ML_cs", "kpi": {"kpi_2y": {"Net_Profit": "88.276w", "Max_Drawdown": "8.263w", "Ann_Sharpe": "3.585", "Daily_Std": "0.809w"}, "kpi_6m": {"Net_Profit": "19.685w", "Max_Drawdown": "6.128w", "Ann_Sharpe": "2.940", "Daily_Std": "0.920w"}}, "children": [], "ratio": 10.0}], "ratio": 12.0}