{"name": "pyelf_21ENetLong_nexrem_onlygap_tp100_day_2025wf", "kpi": {"kpi_2y": {"Net_Profit": "552.529w", "Max_Drawdown": "437.325w", "Ann_Sharpe": "0.648", "Daily_Std": "27.952w"}, "kpi_6m": {"Net_Profit": "67.485w", "Max_Drawdown": "437.325w", "Ann_Sharpe": "0.252", "Daily_Std": "36.432w"}}, "children": [{"name": "pyelf_21ENet5MDiffYP3_nexrem_onlygap_tp100_day_2025wf", "kpi": {"kpi_2y": {"Net_Profit": "617.136w", "Max_Drawdown": "422.613w", "Ann_Sharpe": "0.726", "Daily_Std": "27.884w"}, "kpi_6m": {"Net_Profit": "73.939w", "Max_Drawdown": "422.613w", "Ann_Sharpe": "0.276", "Daily_Std": "36.471w"}}, "children": [], "ratio": 33.0}, {"name": "pyelf_21ENet5MDiffYP5_nexrem_onlygap_tp100_day_2025wf", "kpi": {"kpi_2y": {"Net_Profit": "566.060w", "Max_Drawdown": "455.465w", "Ann_Sharpe": "0.656", "Daily_Std": "28.322w"}, "kpi_6m": {"Net_Profit": "44.635w", "Max_Drawdown": "455.465w", "Ann_Sharpe": "0.165", "Daily_Std": "36.803w"}}, "children": [], "ratio": 33.0}, {"name": "pyelf_21ENet6MDiffYP5_nexrem_onlygap_tp100_day_2025wf", "kpi": {"kpi_2y": {"Net_Profit": "490.625w", "Max_Drawdown": "434.247w", "Ann_Sharpe": "0.579", "Daily_Std": "27.791w"}, "kpi_6m": {"Net_Profit": "90.104w", "Max_Drawdown": "434.247w", "Ann_Sharpe": "0.339", "Daily_Std": "36.225w"}}, "children": [], "ratio": 34.0}], "ratio": 21.67}