{"name": "pyelf_25EnetLong_NExrem", "kpi": {"kpi_2y": {"Net_Profit": "30.721w", "Max_Drawdown": "14.900w", "Ann_Sharpe": "0.969", "Daily_Std": "1.035w"}, "kpi_6m": {"Net_Profit": "-1.011w", "Max_Drawdown": "14.900w", "Ann_Sharpe": "-0.112", "Daily_Std": "1.239w"}}, "children": [{"name": "pyelf_21ENetLong_newfilter_nexrem_tp50_sharperatio_2025wf", "kpi": {"kpi_2y": {"Net_Profit": "287.106w", "Max_Drawdown": "105.203w", "Ann_Sharpe": "1.157", "Daily_Std": "8.108w"}, "kpi_6m": {"Net_Profit": "-67.610w", "Max_Drawdown": "105.203w", "Ann_Sharpe": "-1.224", "Daily_Std": "7.594w"}}, "children": [], "ratio": 1.869624829, "_drillable": true}, {"name": "pyelf_21ENetLong_newfilter_nexrem_tp50_totalreturn_2025wf", "kpi": {"kpi_2y": {"Net_Profit": "318.356w", "Max_Drawdown": "184.918w", "Ann_Sharpe": "1.018", "Daily_Std": "10.215w"}, "kpi_6m": {"Net_Profit": "-82.759w", "Max_Drawdown": "105.133w", "Ann_Sharpe": "-1.283", "Daily_Std": "8.871w"}}, "children": [], "ratio": 1.489129356, "_drillable": true}, {"name": "pyelf_21ENetLong_newfilter_nexrem_tp100_sharperatio_2025wf", "kpi": {"kpi_2y": {"Net_Profit": "454.760w", "Max_Drawdown": "247.162w", "Ann_Sharpe": "0.883", "Daily_Std": "16.833w"}, "kpi_6m": {"Net_Profit": "37.587w", "Max_Drawdown": "247.162w", "Ann_Sharpe": "0.237", "Daily_Std": "21.778w"}}, "children": [], "ratio": 2.23442288, "_drillable": true}, {"name": "pyelf_21ENetLong_newfilter_nexrem_tp100_totalreturn_2025wf", "kpi": {"kpi_2y": {"Net_Profit": "523.241w", "Max_Drawdown": "327.553w", "Ann_Sharpe": "0.863", "Daily_Std": "19.817w"}, "kpi_6m": {"Net_Profit": "25.560w", "Max_Drawdown": "327.553w", "Ann_Sharpe": "0.133", "Daily_Std": "26.371w"}}, "children": [], "ratio": 1.947040498, "_drillable": true}], "ratio": 3.0}