{"name": "pyelf_21ENetMid_MonthDiff_2023wf", "kpi": {"kpi_2y": {"Net_Profit": "42.261w", "Max_Drawdown": "44.180w", "Ann_Sharpe": "0.484", "Daily_Std": "2.858w"}, "kpi_6m": {"Net_Profit": "45.477w", "Max_Drawdown": "12.608w", "Ann_Sharpe": "1.902", "Daily_Std": "3.259w"}}, "children": [{"name": "pyelf_21ENetMLSigFilter3WholeMonthDiff_110minYP128TP25_day_2023wf", "kpi": {"kpi_2y": {"Net_Profit": "32.137w", "Max_Drawdown": "40.764w", "Ann_Sharpe": "0.338", "Daily_Std": "3.110w"}, "kpi_6m": {"Net_Profit": "28.796w", "Max_Drawdown": "18.666w", "Ann_Sharpe": "0.932", "Daily_Std": "4.214w"}}, "children": [], "ratio": 13.39712942}, {"name": "pyelf_21ENetMLSigFilter3WholeMonthDiff_110minYP64TP25_day_2023wf", "kpi": {"kpi_2y": {"Net_Profit": "43.036w", "Max_Drawdown": "40.035w", "Ann_Sharpe": "0.407", "Daily_Std": "3.463w"}, "kpi_6m": {"Net_Profit": "41.535w", "Max_Drawdown": "19.358w", "Ann_Sharpe": "1.354", "Daily_Std": "4.181w"}}, "children": [], "ratio": 12.16495197}, {"name": "pyelf_21ENetMLSigFilter3WholeMonthDiff_130minYP128TP25_day_2023wf", "kpi": {"kpi_2y": {"Net_Profit": "33.406w", "Max_Drawdown": "31.273w", "Ann_Sharpe": "0.434", "Daily_Std": "2.519w"}, "kpi_6m": {"Net_Profit": "11.972w", "Max_Drawdown": "10.315w", "Ann_Sharpe": "0.730", "Daily_Std": "2.235w"}}, "children": [], "ratio": 10.88040873}, {"name": "pyelf_21ENetMLSigFilter3WholeMonthDiff_50minYP256TP15_daynight_2023wf", "kpi": {"kpi_2y": {"Net_Profit": "77.933w", "Max_Drawdown": "42.050w", "Ann_Sharpe": "0.924", "Daily_Std": "2.761w"}, "kpi_6m": {"Net_Profit": "69.157w", "Max_Drawdown": "11.828w", "Ann_Sharpe": "3.179", "Daily_Std": "2.965w"}}, "children": [], "ratio": 17.44518292}, {"name": "pyelf_21ENetMLSigFilter3WholeMonthDiff_50minYP256TP25_day_2023wf", "kpi": {"kpi_2y": {"Net_Profit": "59.720w", "Max_Drawdown": "48.697w", "Ann_Sharpe": "0.487", "Daily_Std": "4.016w"}, "kpi_6m": {"Net_Profit": "54.236w", "Max_Drawdown": "20.523w", "Ann_Sharpe": "1.587", "Daily_Std": "4.659w"}}, "children": [], "ratio": 10.47917211}, {"name": "pyelf_21ENetMLSigFilter3WholeMonthDiff_50minYP64TP15_daynight_2023wf", "kpi": {"kpi_2y": {"Net_Profit": "49.340w", "Max_Drawdown": "57.647w", "Ann_Sharpe": "0.507", "Daily_Std": "3.184w"}, "kpi_6m": {"Net_Profit": "54.016w", "Max_Drawdown": "15.236w", "Ann_Sharpe": "2.123", "Daily_Std": "3.467w"}}, "children": [], "ratio": 15.44509825}, {"name": "pyelf_21ENetMLSigFilter6WholeMonthDiff_70minYP64TP25_daynight_2023wf", "kpi": {"kpi_2y": {"Net_Profit": "-14.526w", "Max_Drawdown": "122.091w", "Ann_Sharpe": "-0.109", "Daily_Std": "4.378w"}, "kpi_6m": {"Net_Profit": "38.187w", "Max_Drawdown": "26.469w", "Ann_Sharpe": "1.125", "Daily_Std": "4.627w"}}, "children": [], "ratio": 9.967992981}, {"name": "pyelf_21ENetMLSigFilter3WholeMonthDiff_70minYP64TP25_day_2023wf", "kpi": {"kpi_2y": {"Net_Profit": "26.221w", "Max_Drawdown": "110.150w", "Ann_Sharpe": "0.199", "Daily_Std": "4.310w"}, "kpi_6m": {"Net_Profit": "50.803w", "Max_Drawdown": "22.606w", "Ann_Sharpe": "1.346", "Daily_Std": "5.143w"}}, "children": [], "ratio": 10.22006361}], "ratio": 64.0}