{"name": "pyelf_21ENetLong_newfilter_nexrem_tp100_sharperatio_2025wf", "kpi": {"kpi_2y": {"Net_Profit": "633.402w", "Max_Drawdown": "188.954w", "Ann_Sharpe": "1.179", "Daily_Std": "17.630w"}, "kpi_6m": {"Net_Profit": "131.658w", "Max_Drawdown": "188.954w", "Ann_Sharpe": "0.814", "Daily_Std": "21.862w"}}, "children": [{"name": "pyelf_21ENetLong_nexrem_parkinson_tp100_day_2025wf", "kpi": {"kpi_2y": {"Net_Profit": "414.754w", "Max_Drawdown": "294.939w", "Ann_Sharpe": "0.641", "Daily_Std": "21.231w"}, "kpi_6m": {"Net_Profit": "-123.486w", "Max_Drawdown": "215.091w", "Ann_Sharpe": "-0.874", "Daily_Std": "19.102w"}}, "children": [], "ratio": 18.71, "_drillable": true}, {"name": "pyelf_21ENetLong_nexrem_onlyyzvol_tp100_day_2025wf", "kpi": {"kpi_2y": {"Net_Profit": "994.840w", "Max_Drawdown": "362.016w", "Ann_Sharpe": "1.149", "Daily_Std": "28.404w"}, "kpi_6m": {"Net_Profit": "325.221w", "Max_Drawdown": "362.016w", "Ann_Sharpe": "1.081", "Daily_Std": "40.642w"}}, "children": [], "ratio": 18.02, "_drillable": true}, {"name": "pyelf_21ENetLong_nexrem_ewma_tp100_day_2025wf", "kpi": {"kpi_2y": {"Net_Profit": "203.346w", "Max_Drawdown": "147.264w", "Ann_Sharpe": "0.553", "Daily_Std": "12.058w"}, "kpi_6m": {"Net_Profit": "83.920w", "Max_Drawdown": "90.330w", "Ann_Sharpe": "0.789", "Daily_Std": "14.373w"}}, "children": [], "ratio": 16.79, "_drillable": true}, {"name": "pyelf_21ENet5MDiffYP3_nexrem_yzvol_tp100_day_2025wf", "kpi": {"kpi_2y": {"Net_Profit": "981.979w", "Max_Drawdown": "342.205w", "Ann_Sharpe": "1.091", "Daily_Std": "29.513w"}, "kpi_6m": {"Net_Profit": "240.464w", "Max_Drawdown": "342.205w", "Ann_Sharpe": "0.814", "Daily_Std": "39.946w"}}, "children": [], "ratio": 19.53}, {"name": "pyelf_21ENetLong_nexrem_onlyadx_tp100_day_2025wf", "kpi": {"kpi_2y": {"Net_Profit": "560.620w", "Max_Drawdown": "87.705w", "Ann_Sharpe": "2.349", "Daily_Std": "7.830w"}, "kpi_6m": {"Net_Profit": "135.666w", "Max_Drawdown": "87.705w", "Ann_Sharpe": "1.906", "Daily_Std": "9.620w"}}, "children": [], "ratio": 26.95, "_drillable": true}], "ratio": 2.23442288}