{"name": "pyelf_21EnetLong_BIGTPSS", "kpi": {"kpi_2y": {"Net_Profit": "27.256w", "Max_Drawdown": "10.697w", "Ann_Sharpe": "0.847", "Daily_Std": "1.054w"}, "kpi_6m": {"Net_Profit": "2.299w", "Max_Drawdown": "10.697w", "Ann_Sharpe": "0.289", "Daily_Std": "1.083w"}}, "children": [{"name": "pyelf_21ENetMLSig5WholeMonthDiff_360minYP3TP50_day_2024_SS", "kpi": {"kpi_2y": {"Net_Profit": "41.487w", "Max_Drawdown": "12.324w", "Ann_Sharpe": "0.973", "Daily_Std": "1.396w"}, "kpi_6m": {"Net_Profit": "4.971w", "Max_Drawdown": "8.839w", "Ann_Sharpe": "0.514", "Daily_Std": "1.319w"}}, "children": [], "ratio": 15.921}, {"name": "pyelf_21ENetMLSig5WholeMonthDiff_360minYP3TP100_day_2024_SS", "kpi": {"kpi_2y": {"Net_Profit": "49.268w", "Max_Drawdown": "20.113w", "Ann_Sharpe": "0.877", "Daily_Std": "1.840w"}, "kpi_6m": {"Net_Profit": "3.157w", "Max_Drawdown": "20.113w", "Ann_Sharpe": "0.225", "Daily_Std": "1.910w"}}, "children": [], "ratio": 46.383}], "ratio": 4.0}