{"name": "pyelf_21ENetlong_adx_tp50_day_2025wf", "kpi": {"kpi_2y": {"Net_Profit": "255.660w", "Max_Drawdown": "39.620w", "Ann_Sharpe": "2.100", "Daily_Std": "3.993w"}, "kpi_6m": {"Net_Profit": "-7.155w", "Max_Drawdown": "39.620w", "Ann_Sharpe": "-0.238", "Daily_Std": "4.028w"}}, "children": [{"name": "pyelf_21ENet6MDiffYP5_adx_tp50_day_2025wf", "kpi": {"kpi_2y": {"Net_Profit": "258.170w", "Max_Drawdown": "39.441w", "Ann_Sharpe": "2.191", "Daily_Std": "3.866w"}, "kpi_6m": {"Net_Profit": "6.612w", "Max_Drawdown": "39.441w", "Ann_Sharpe": "0.215", "Daily_Std": "4.119w"}}, "children": [], "ratio": 34.0}, {"name": "pyelf_21ENet5MDiffYP5_adx_tp50_day_2025wf", "kpi": {"kpi_2y": {"Net_Profit": "262.342w", "Max_Drawdown": "39.420w", "Ann_Sharpe": "2.160", "Daily_Std": "3.984w"}, "kpi_6m": {"Net_Profit": "-7.363w", "Max_Drawdown": "39.420w", "Ann_Sharpe": "-0.257", "Daily_Std": "3.833w"}}, "children": [], "ratio": 33.0}, {"name": "pyelf_21ENet5MDiffYP3_adx_tp50_day_2025wf", "kpi": {"kpi_2y": {"Net_Profit": "259.070w", "Max_Drawdown": "54.027w", "Ann_Sharpe": "1.958", "Daily_Std": "4.341w"}, "kpi_6m": {"Net_Profit": "-8.690w", "Max_Drawdown": "40.715w", "Ann_Sharpe": "-0.265", "Daily_Std": "4.393w"}}, "children": [], "ratio": 33.0}], "ratio": 25.89}