{"name": "pyelf_21ENetlong_adx_tp50_day_2025wf", "kpi": {"kpi_2y": {"Net_Profit": "239.848w", "Max_Drawdown": "41.067w", "Ann_Sharpe": "1.990", "Daily_Std": "3.954w"}, "kpi_6m": {"Net_Profit": "-10.027w", "Max_Drawdown": "41.067w", "Ann_Sharpe": "-0.340", "Daily_Std": "4.014w"}}, "children": [{"name": "pyelf_21ENet6MDiffYP5_adx_tp50_day_2025wf", "kpi": {"kpi_2y": {"Net_Profit": "241.905w", "Max_Drawdown": "40.363w", "Ann_Sharpe": "2.072", "Daily_Std": "3.831w"}, "kpi_6m": {"Net_Profit": "0.197w", "Max_Drawdown": "40.363w", "Ann_Sharpe": "0.007", "Daily_Std": "4.106w"}}, "children": [], "ratio": 34.0}, {"name": "pyelf_21ENet5MDiffYP5_adx_tp50_day_2025wf", "kpi": {"kpi_2y": {"Net_Profit": "250.237w", "Max_Drawdown": "42.256w", "Ann_Sharpe": "2.076", "Daily_Std": "3.955w"}, "kpi_6m": {"Net_Profit": "-9.492w", "Max_Drawdown": "42.256w", "Ann_Sharpe": "-0.338", "Daily_Std": "3.822w"}}, "children": [], "ratio": 33.0}, {"name": "pyelf_21ENet5MDiffYP3_adx_tp50_day_2025wf", "kpi": {"kpi_2y": {"Net_Profit": "240.019w", "Max_Drawdown": "54.027w", "Ann_Sharpe": "1.839", "Daily_Std": "4.280w"}, "kpi_6m": {"Net_Profit": "-8.732w", "Max_Drawdown": "40.715w", "Ann_Sharpe": "-0.274", "Daily_Std": "4.347w"}}, "children": [], "ratio": 33.0}], "ratio": 25.89}