{"name": "pyelf_21ENetShort_MonthDiff_20minplus_2023wf", "kpi": {"kpi_2y": {"Net_Profit": "20.266w", "Max_Drawdown": "100.154w", "Ann_Sharpe": "0.191", "Daily_Std": "3.472w"}, "kpi_6m": {"Net_Profit": "38.166w", "Max_Drawdown": "20.116w", "Ann_Sharpe": "1.425", "Daily_Std": "3.650w"}}, "children": [{"name": "pyelf_21ENetMLSigFilter3WholeMonthDiff_24minYP32TP15_day_2023wf", "kpi": {"kpi_2y": {"Net_Profit": "-27.631w", "Max_Drawdown": "126.064w", "Ann_Sharpe": "-0.270", "Daily_Std": "3.352w"}, "kpi_6m": {"Net_Profit": "28.605w", "Max_Drawdown": "23.691w", "Ann_Sharpe": "1.213", "Daily_Std": "3.214w"}}, "children": [], "ratio": 15.2677124}, {"name": "pyelf_21ENetMLSigFilter3WholeMonthDiff_37minYP16TP15_daynight_2023wf", "kpi": {"kpi_2y": {"Net_Profit": "-21.378w", "Max_Drawdown": "92.774w", "Ann_Sharpe": "-0.238", "Daily_Std": "2.947w"}, "kpi_6m": {"Net_Profit": "-8.625w", "Max_Drawdown": "32.422w", "Ann_Sharpe": "-0.510", "Daily_Std": "2.305w"}}, "children": [], "ratio": 13.29072443}, {"name": "pyelf_21ENetMLSigFilter3WholeMonthDiff_38minYP16TP25_day_2023wf", "kpi": {"kpi_2y": {"Net_Profit": "54.329w", "Max_Drawdown": "98.768w", "Ann_Sharpe": "0.403", "Daily_Std": "4.423w"}, "kpi_6m": {"Net_Profit": "68.825w", "Max_Drawdown": "46.649w", "Ann_Sharpe": "1.516", "Daily_Std": "6.188w"}}, "children": [], "ratio": 10.88367737}, {"name": "pyelf_21ENetMLSigFilter3WholeMonthDiff_34minYP128TP25_daynight_2023wf", "kpi": {"kpi_2y": {"Net_Profit": "11.847w", "Max_Drawdown": "116.543w", "Ann_Sharpe": "0.089", "Daily_Std": "4.376w"}, "kpi_6m": {"Net_Profit": "34.734w", "Max_Drawdown": "28.023w", "Ann_Sharpe": "1.153", "Daily_Std": "4.106w"}}, "children": [], "ratio": 12.75948535}, {"name": "pyelf_21ENetMLSigFilter3WholeMonthDiff_21minYP128TP15_daynight_2023wf", "kpi": {"kpi_2y": {"Net_Profit": "6.809w", "Max_Drawdown": "40.933w", "Ann_Sharpe": "0.149", "Daily_Std": "1.497w"}, "kpi_6m": {"Net_Profit": "14.584w", "Max_Drawdown": "7.340w", "Ann_Sharpe": "1.411", "Daily_Std": "1.409w"}}, "children": [], "ratio": 27.14127656}, {"name": "pyelf_21ENetMLSigFilter3WholeMonthDiff_25minYP16TP35_day_2023wf", "kpi": {"kpi_2y": {"Net_Profit": "57.910w", "Max_Drawdown": "144.230w", "Ann_Sharpe": "0.368", "Daily_Std": "5.168w"}, "kpi_6m": {"Net_Profit": "72.885w", "Max_Drawdown": "23.532w", "Ann_Sharpe": "1.749", "Daily_Std": "5.679w"}}, "children": [], "ratio": 12.09423586}, {"name": "pyelf_21ENetMLSigFilter3WholeMonthDiff_36minYP32TP15_daynight_2023wf", "kpi": {"kpi_2y": {"Net_Profit": "3.181w", "Max_Drawdown": "81.836w", "Ann_Sharpe": "0.034", "Daily_Std": "3.085w"}, "kpi_6m": {"Net_Profit": "18.374w", "Max_Drawdown": "16.421w", "Ann_Sharpe": "0.991", "Daily_Std": "2.527w"}}, "children": [], "ratio": 13.97394239}, {"name": "pyelf_21ENetMLSigFilter3WholeMonthDiff_36minYP128TP35_day_2023wf", "kpi": {"kpi_2y": {"Net_Profit": "89.271w", "Max_Drawdown": "81.698w", "Ann_Sharpe": "0.538", "Daily_Std": "5.446w"}, "kpi_6m": {"Net_Profit": "67.808w", "Max_Drawdown": "43.359w", "Ann_Sharpe": "1.267", "Daily_Std": "7.295w"}}, "children": [], "ratio": 10.77915631}], "ratio": 47.83423627}