{"name": "pyelf_21ENetLong_onlyyzvol_tp100_day_2025wf", "kpi": {"kpi_2y": {"Net_Profit": "668.931w", "Max_Drawdown": "398.742w", "Ann_Sharpe": "0.861", "Daily_Std": "25.491w"}, "kpi_6m": {"Net_Profit": "101.751w", "Max_Drawdown": "398.742w", "Ann_Sharpe": "0.391", "Daily_Std": "35.760w"}}, "children": [{"name": "pyelf_21ENet5MDiffYP3_onlyyzvol_tp100_day_2025wf", "kpi": {"kpi_2y": {"Net_Profit": "679.753w", "Max_Drawdown": "411.820w", "Ann_Sharpe": "0.872", "Daily_Std": "25.569w"}, "kpi_6m": {"Net_Profit": "74.150w", "Max_Drawdown": "411.820w", "Ann_Sharpe": "0.286", "Daily_Std": "35.674w"}}, "children": [], "ratio": 34.0}, {"name": "pyelf_21ENet5MDiffYP5_onlyyzvol_tp100_day_2025wf", "kpi": {"kpi_2y": {"Net_Profit": "685.047w", "Max_Drawdown": "391.180w", "Ann_Sharpe": "0.878", "Daily_Std": "25.594w"}, "kpi_6m": {"Net_Profit": "126.434w", "Max_Drawdown": "391.180w", "Ann_Sharpe": "0.486", "Daily_Std": "35.786w"}}, "children": [], "ratio": 33.0}, {"name": "pyelf_21ENet6MDiffYP5_onlyyzvol_tp100_day_2025wf", "kpi": {"kpi_2y": {"Net_Profit": "638.277w", "Max_Drawdown": "393.171w", "Ann_Sharpe": "0.824", "Daily_Std": "25.416w"}, "kpi_6m": {"Net_Profit": "102.666w", "Max_Drawdown": "393.171w", "Ann_Sharpe": "0.393", "Daily_Std": "35.958w"}}, "children": [], "ratio": 33.0}], "ratio": 19.42}