{"name": "pyelf_21ENetLong_nexrem_parkinson_tp50_day_2025wf", "kpi": {"kpi_2y": {"Net_Profit": "392.629w", "Max_Drawdown": "314.393w", "Ann_Sharpe": "0.895", "Daily_Std": "14.362w"}, "kpi_6m": {"Net_Profit": "-134.411w", "Max_Drawdown": "166.950w", "Ann_Sharpe": "-1.232", "Daily_Std": "14.616w"}}, "children": [{"name": "pyelf_21ENet5MDiffYP3_nexrem_onlyparkinson_tp50_day_2025wf", "kpi": {"kpi_2y": {"Net_Profit": "406.111w", "Max_Drawdown": "328.007w", "Ann_Sharpe": "0.916", "Daily_Std": "14.514w"}, "kpi_6m": {"Net_Profit": "-146.536w", "Max_Drawdown": "161.600w", "Ann_Sharpe": "-1.363", "Daily_Std": "14.410w"}}, "children": [], "ratio": 34.0}, {"name": "pyelf_21ENet5MDiffYP5_nexrem_onlyparkinson_tp50_day_2025wf", "kpi": {"kpi_2y": {"Net_Profit": "364.618w", "Max_Drawdown": "322.706w", "Ann_Sharpe": "0.851", "Daily_Std": "14.033w"}, "kpi_6m": {"Net_Profit": "-140.761w", "Max_Drawdown": "160.941w", "Ann_Sharpe": "-1.318", "Daily_Std": "14.316w"}}, "children": [], "ratio": 34.0}, {"name": "pyelf_21ENet6MDiffYP5_nexrem_onlyparkinson_tp50_day_2025wf", "kpi": {"kpi_2y": {"Net_Profit": "408.149w", "Max_Drawdown": "290.974w", "Ann_Sharpe": "0.910", "Daily_Std": "14.687w"}, "kpi_6m": {"Net_Profit": "-114.466w", "Max_Drawdown": "179.033w", "Ann_Sharpe": "-0.998", "Daily_Std": "15.366w"}}, "children": [], "ratio": 32.0}], "ratio": 22.55}