{"name": "pyelf_21ENetLong_nexrem_parkinson_tp100_day_2025wf", "kpi": {"kpi_2y": {"Net_Profit": "231.119w", "Max_Drawdown": "339.814w", "Ann_Sharpe": "0.362", "Daily_Std": "20.872w"}, "kpi_6m": {"Net_Profit": "-222.034w", "Max_Drawdown": "259.966w", "Ann_Sharpe": "-1.637", "Daily_Std": "18.652w"}}, "children": [{"name": "pyelf_21ENet5MDiffYP3_nexrem_parkinson_tp100_day_2025wf", "kpi": {"kpi_2y": {"Net_Profit": "300.658w", "Max_Drawdown": "246.924w", "Ann_Sharpe": "0.471", "Daily_Std": "20.882w"}, "kpi_6m": {"Net_Profit": "-144.328w", "Max_Drawdown": "246.535w", "Ann_Sharpe": "-0.983", "Daily_Std": "20.183w"}}, "children": [], "ratio": 33.0}, {"name": "pyelf_21ENet5MDiffYP5_nexrem_parkinson_tp100_day_2025wf", "kpi": {"kpi_2y": {"Net_Profit": "279.606w", "Max_Drawdown": "364.798w", "Ann_Sharpe": "0.423", "Daily_Std": "21.647w"}, "kpi_6m": {"Net_Profit": "-231.923w", "Max_Drawdown": "272.427w", "Ann_Sharpe": "-1.598", "Daily_Std": "19.959w"}}, "children": [], "ratio": 34.0}, {"name": "pyelf_21ENet6MDiffYP5_nexrem_parkinson_tp100_day_2025wf", "kpi": {"kpi_2y": {"Net_Profit": "124.544w", "Max_Drawdown": "403.724w", "Ann_Sharpe": "0.199", "Daily_Std": "20.456w"}, "kpi_6m": {"Net_Profit": "-285.671w", "Max_Drawdown": "318.165w", "Ann_Sharpe": "-2.378", "Daily_Std": "16.520w"}}, "children": [], "ratio": 33.0}], "ratio": 23.8}