{"name": "pyelf_21ENetLong_nexrem_adx_tp50_day_2025wf", "kpi": {"kpi_2y": {"Net_Profit": "401.548w", "Max_Drawdown": "100.429w", "Ann_Sharpe": "1.886", "Daily_Std": "6.999w"}, "kpi_6m": {"Net_Profit": "8.415w", "Max_Drawdown": "100.429w", "Ann_Sharpe": "0.142", "Daily_Std": "7.952w"}}, "children": [{"name": "pyelf_21ENet5MDiffYP3_nexrem_adx_tp50_day_2025wf", "kpi": {"kpi_2y": {"Net_Profit": "411.252w", "Max_Drawdown": "111.428w", "Ann_Sharpe": "1.870", "Daily_Std": "7.230w"}, "kpi_6m": {"Net_Profit": "-3.757w", "Max_Drawdown": "111.428w", "Ann_Sharpe": "-0.057", "Daily_Std": "8.829w"}}, "children": [], "ratio": 33.0}, {"name": "pyelf_21ENet5MDiffYP5_nexrem_adx_tp50_day_2025wf", "kpi": {"kpi_2y": {"Net_Profit": "401.594w", "Max_Drawdown": "97.831w", "Ann_Sharpe": "1.785", "Daily_Std": "7.394w"}, "kpi_6m": {"Net_Profit": "3.426w", "Max_Drawdown": "97.831w", "Ann_Sharpe": "0.059", "Daily_Std": "7.771w"}}, "children": [], "ratio": 33.0}, {"name": "pyelf_21ENet6MDiffYP5_nexrem_adx_tp50_day_2025wf", "kpi": {"kpi_2y": {"Net_Profit": "398.892w", "Max_Drawdown": "92.289w", "Ann_Sharpe": "1.962", "Daily_Std": "6.684w"}, "kpi_6m": {"Net_Profit": "28.570w", "Max_Drawdown": "92.289w", "Ann_Sharpe": "0.503", "Daily_Std": "7.612w"}}, "children": [], "ratio": 34.0}], "ratio": 21.37}