{"name": "pyelf_21ENetLong_newfilter_nexrem_tp50_totalreturn_2025wf", "kpi": {"kpi_2y": {"Net_Profit": "325.704w", "Max_Drawdown": "184.918w", "Ann_Sharpe": "1.045", "Daily_Std": "10.242w"}, "kpi_6m": {"Net_Profit": "-74.185w", "Max_Drawdown": "105.133w", "Ann_Sharpe": "-1.137", "Daily_Std": "8.971w"}}, "children": [{"name": "pyelf_21ENetLong_nexrem_parkinson_tp50_day_2025wf", "kpi": {"kpi_2y": {"Net_Profit": "293.098w", "Max_Drawdown": "342.830w", "Ann_Sharpe": "0.696", "Daily_Std": "13.835w"}, "kpi_6m": {"Net_Profit": "-137.843w", "Max_Drawdown": "195.386w", "Ann_Sharpe": "-1.243", "Daily_Std": "15.248w"}}, "children": [], "ratio": 22.55, "_drillable": true}, {"name": "pyelf_21ENetLong_nexrem_onlyparkinson_tp50_day_2025wf", "kpi": {"kpi_2y": {"Net_Profit": "293.106w", "Max_Drawdown": "342.822w", "Ann_Sharpe": "0.696", "Daily_Std": "13.835w"}, "kpi_6m": {"Net_Profit": "-137.843w", "Max_Drawdown": "195.386w", "Ann_Sharpe": "-1.243", "Daily_Std": "15.248w"}}, "children": [], "ratio": 13.29, "_drillable": true}, {"name": "pyelf_21ENetLong_nexrem_onlyvolasingle_tp50_day_2025wf", "kpi": {"kpi_2y": {"Net_Profit": "352.560w", "Max_Drawdown": "146.793w", "Ann_Sharpe": "1.065", "Daily_Std": "10.882w"}, "kpi_6m": {"Net_Profit": "-36.943w", "Max_Drawdown": "66.250w", "Ann_Sharpe": "-0.671", "Daily_Std": "7.567w"}}, "children": [], "ratio": 20.06, "_drillable": true}, {"name": "pyelf_21ENetLong_nexrem_annualvol_tp50_day_2025wf", "kpi": {"kpi_2y": {"Net_Profit": "299.211w", "Max_Drawdown": "161.384w", "Ann_Sharpe": "0.742", "Daily_Std": "13.251w"}, "kpi_6m": {"Net_Profit": "-84.773w", "Max_Drawdown": "134.398w", "Ann_Sharpe": "-1.060", "Daily_Std": "11.000w"}}, "children": [], "ratio": 20.42, "_drillable": true}, {"name": "pyelf_21ENetLong_nexrem_onlyadx_tp50_day_2025wf", "kpi": {"kpi_2y": {"Net_Profit": "384.735w", "Max_Drawdown": "69.027w", "Ann_Sharpe": "2.028", "Daily_Std": "6.237w"}, "kpi_6m": {"Net_Profit": "10.405w", "Max_Drawdown": "69.027w", "Ann_Sharpe": "0.244", "Daily_Std": "5.872w"}}, "children": [], "ratio": 23.68, "_drillable": true}], "ratio": 1.489129356}