{"name": "ifp_complex_group", "kpi": {"kpi_2y": {"Net_Profit": "139.913w", "Max_Drawdown": "8.321w", "Ann_Sharpe": "3.660", "Daily_Std": "1.251w"}, "kpi_6m": {"Net_Profit": "18.579w", "Max_Drawdown": "5.639w", "Ann_Sharpe": "2.067", "Daily_Std": "1.184w"}}, "children": [{"name": "ifp_alpha_group", "kpi": {"kpi_2y": {"Net_Profit": "78.137w", "Max_Drawdown": "8.921w", "Ann_Sharpe": "3.181", "Daily_Std": "0.804w"}, "kpi_6m": {"Net_Profit": "5.512w", "Max_Drawdown": "8.921w", "Ann_Sharpe": "0.785", "Daily_Std": "0.925w"}}, "children": [], "ratio": 87.087, "_drillable": true}, {"name": "ifp_beta_group", "kpi": {"kpi_2y": {"Net_Profit": "64.841w", "Max_Drawdown": "6.139w", "Ann_Sharpe": "2.573", "Daily_Std": "0.825w"}, "kpi_6m": {"Net_Profit": "16.546w", "Max_Drawdown": "5.726w", "Ann_Sharpe": "2.829", "Daily_Std": "0.771w"}}, "children": [], "ratio": 71.808, "_drillable": true}, {"name": "ifp_longonly_group", "kpi": {"kpi_2y": {"Net_Profit": "75.056w", "Max_Drawdown": "19.948w", "Ann_Sharpe": "1.421", "Daily_Std": "1.729w"}, "kpi_6m": {"Net_Profit": "40.893w", "Max_Drawdown": "12.606w", "Ann_Sharpe": "2.671", "Daily_Std": "2.017w"}}, "children": [], "ratio": 15.95, "_drillable": true}], "ratio": 3.141}