{"name": "tengfeng_500w_202603", "kpi": {"kpi_2y": {"Net_Profit": "391.918w", "Max_Drawdown": "30.170w", "Ann_Sharpe": "3.502", "Daily_Std": "3.664w"}, "kpi_6m": {"Net_Profit": "84.048w", "Max_Drawdown": "30.170w", "Ann_Sharpe": "2.796", "Daily_Std": "4.097w"}}, "children": [{"name": "all_weather_group_202512", "kpi": {"kpi_2y": {"Net_Profit": "305.085w", "Max_Drawdown": "36.168w", "Ann_Sharpe": "2.476", "Daily_Std": "4.033w"}, "kpi_6m": {"Net_Profit": "61.748w", "Max_Drawdown": "36.168w", "Ann_Sharpe": "1.806", "Daily_Std": "4.660w"}}, "children": [], "ratio": 25.9495164, "_drillable": true}, {"name": "all_weather_group_202603", "kpi": {"kpi_2y": {"Net_Profit": "251.811w", "Max_Drawdown": "31.653w", "Ann_Sharpe": "2.380", "Daily_Std": "3.464w"}, "kpi_6m": {"Net_Profit": "52.293w", "Max_Drawdown": "30.517w", "Ann_Sharpe": "1.858", "Daily_Std": "3.837w"}}, "children": [], "ratio": 33.18019398, "_drillable": true}, {"name": "sentiment_group_202511", "kpi": {"kpi_2y": {"Net_Profit": "318.114w", "Max_Drawdown": "19.829w", "Ann_Sharpe": "2.978", "Daily_Std": "3.497w"}, "kpi_6m": {"Net_Profit": "29.645w", "Max_Drawdown": "19.829w", "Ann_Sharpe": "1.563", "Daily_Std": "2.586w"}}, "children": [], "ratio": 9.458948165, "_drillable": true}, {"name": "sentiment_group_202512", "kpi": {"kpi_2y": {"Net_Profit": "288.227w", "Max_Drawdown": "14.012w", "Ann_Sharpe": "3.232", "Daily_Std": "2.920w"}, "kpi_6m": {"Net_Profit": "52.337w", "Max_Drawdown": "14.012w", "Ann_Sharpe": "2.430", "Daily_Std": "2.936w"}}, "children": [], "ratio": 21.73125679, "_drillable": true}, {"name": "volume_price_202511", "kpi": {"kpi_2y": {"Net_Profit": "311.181w", "Max_Drawdown": "30.797w", "Ann_Sharpe": "2.982", "Daily_Std": "3.417w"}, "kpi_6m": {"Net_Profit": "62.060w", "Max_Drawdown": "30.797w", "Ann_Sharpe": "2.203", "Daily_Std": "3.840w"}}, "children": [], "ratio": 3.825554705, "_drillable": true}, {"name": "volume_price_202601", "kpi": {"kpi_2y": {"Net_Profit": "314.200w", "Max_Drawdown": "31.539w", "Ann_Sharpe": "2.965", "Daily_Std": "3.469w"}, "kpi_6m": {"Net_Profit": "63.520w", "Max_Drawdown": "31.539w", "Ann_Sharpe": "2.178", "Daily_Std": "3.975w"}}, "children": [], "ratio": 3.785966683, "_drillable": true}, {"name": "volume_price_202603", "kpi": {"kpi_2y": {"Net_Profit": "312.451w", "Max_Drawdown": "22.377w", "Ann_Sharpe": "3.229", "Daily_Std": "3.168w"}, "kpi_6m": {"Net_Profit": "91.201w", "Max_Drawdown": "22.377w", "Ann_Sharpe": "3.189", "Daily_Std": "3.898w"}}, "children": [], "ratio": 16.41586867, "_drillable": true}, {"name": "multi_factor_202511", "kpi": {"kpi_2y": {"Net_Profit": "436.529w", "Max_Drawdown": "39.501w", "Ann_Sharpe": "2.919", "Daily_Std": "4.895w"}, "kpi_6m": {"Net_Profit": "93.962w", "Max_Drawdown": "15.299w", "Ann_Sharpe": "3.470", "Daily_Std": "3.691w"}}, "children": [], "ratio": 7.163323782, "_drillable": true}, {"name": "multi_factor_202512", "kpi": {"kpi_2y": {"Net_Profit": "115.753w", "Max_Drawdown": "7.084w", "Ann_Sharpe": "3.504", "Daily_Std": "1.082w"}, "kpi_6m": {"Net_Profit": "20.736w", "Max_Drawdown": "5.773w", "Ann_Sharpe": "3.133", "Daily_Std": "0.902w"}}, "children": [], "ratio": 29.88898377, "_drillable": true}, {"name": "event_driven_202512", "kpi": {"kpi_2y": {"Net_Profit": "179.903w", "Max_Drawdown": "44.461w", "Ann_Sharpe": "1.633", "Daily_Std": "3.606w"}, "kpi_6m": {"Net_Profit": "18.959w", "Max_Drawdown": "44.461w", "Ann_Sharpe": "0.475", "Daily_Std": "5.444w"}}, "children": [], "ratio": 0.216841081, "_drillable": true}, {"name": "event_driven_202603", "kpi": {"kpi_2y": {"Net_Profit": "172.889w", "Max_Drawdown": "43.095w", "Ann_Sharpe": "2.034", "Daily_Std": "2.782w"}, "kpi_6m": {"Net_Profit": "25.469w", "Max_Drawdown": "43.095w", "Ann_Sharpe": "0.874", "Daily_Std": "3.972w"}}, "children": [], "ratio": 3.490401396, "_drillable": true}], "ratio": 108.0}