{"name": "tengfeng_500w_202603", "kpi": {"kpi_2y": {"Net_Profit": "385.803w", "Max_Drawdown": "30.170w", "Ann_Sharpe": "3.436", "Daily_Std": "3.676w"}, "kpi_6m": {"Net_Profit": "87.838w", "Max_Drawdown": "30.170w", "Ann_Sharpe": "2.766", "Daily_Std": "4.184w"}}, "children": [{"name": "all_weather_group_202512", "kpi": {"kpi_2y": {"Net_Profit": "302.878w", "Max_Drawdown": "36.168w", "Ann_Sharpe": "2.456", "Daily_Std": "4.036w"}, "kpi_6m": {"Net_Profit": "67.822w", "Max_Drawdown": "36.168w", "Ann_Sharpe": "1.924", "Daily_Std": "4.645w"}}, "children": [], "ratio": 25.9495164, "_drillable": true}, {"name": "all_weather_group_202603", "kpi": {"kpi_2y": {"Net_Profit": "248.130w", "Max_Drawdown": "31.653w", "Ann_Sharpe": "2.342", "Daily_Std": "3.468w"}, "kpi_6m": {"Net_Profit": "58.157w", "Max_Drawdown": "30.517w", "Ann_Sharpe": "1.998", "Daily_Std": "3.835w"}}, "children": [], "ratio": 33.18019398, "_drillable": true}, {"name": "sentiment_group_202511", "kpi": {"kpi_2y": {"Net_Profit": "314.057w", "Max_Drawdown": "19.829w", "Ann_Sharpe": "2.933", "Daily_Std": "3.506w"}, "kpi_6m": {"Net_Profit": "36.239w", "Max_Drawdown": "19.829w", "Ann_Sharpe": "1.703", "Daily_Std": "2.804w"}}, "children": [], "ratio": 9.458948165, "_drillable": true}, {"name": "sentiment_group_202512", "kpi": {"kpi_2y": {"Net_Profit": "281.057w", "Max_Drawdown": "14.012w", "Ann_Sharpe": "3.128", "Daily_Std": "2.942w"}, "kpi_6m": {"Net_Profit": "62.371w", "Max_Drawdown": "14.012w", "Ann_Sharpe": "2.686", "Daily_Std": "3.060w"}}, "children": [], "ratio": 21.73125679, "_drillable": true}, {"name": "volume_price_202511", "kpi": {"kpi_2y": {"Net_Profit": "308.535w", "Max_Drawdown": "30.797w", "Ann_Sharpe": "2.942", "Daily_Std": "3.433w"}, "kpi_6m": {"Net_Profit": "55.990w", "Max_Drawdown": "30.797w", "Ann_Sharpe": "1.892", "Daily_Std": "3.899w"}}, "children": [], "ratio": 3.825554705, "_drillable": true}, {"name": "volume_price_202601", "kpi": {"kpi_2y": {"Net_Profit": "310.812w", "Max_Drawdown": "31.539w", "Ann_Sharpe": "2.918", "Daily_Std": "3.487w"}, "kpi_6m": {"Net_Profit": "58.698w", "Max_Drawdown": "31.539w", "Ann_Sharpe": "1.930", "Daily_Std": "4.008w"}}, "children": [], "ratio": 3.785966683, "_drillable": true}, {"name": "volume_price_202603", "kpi": {"kpi_2y": {"Net_Profit": "308.304w", "Max_Drawdown": "22.377w", "Ann_Sharpe": "3.164", "Daily_Std": "3.190w"}, "kpi_6m": {"Net_Profit": "85.246w", "Max_Drawdown": "22.377w", "Ann_Sharpe": "2.829", "Daily_Std": "3.971w"}}, "children": [], "ratio": 16.41586867, "_drillable": true}, {"name": "multi_factor_202511", "kpi": {"kpi_2y": {"Net_Profit": "419.433w", "Max_Drawdown": "39.501w", "Ann_Sharpe": "2.795", "Daily_Std": "4.912w"}, "kpi_6m": {"Net_Profit": "95.155w", "Max_Drawdown": "15.299w", "Ann_Sharpe": "3.247", "Daily_Std": "3.862w"}}, "children": [], "ratio": 7.163323782, "_drillable": true}, {"name": "multi_factor_202512", "kpi": {"kpi_2y": {"Net_Profit": "113.935w", "Max_Drawdown": "7.084w", "Ann_Sharpe": "3.425", "Daily_Std": "1.089w"}, "kpi_6m": {"Net_Profit": "21.185w", "Max_Drawdown": "5.773w", "Ann_Sharpe": "2.885", "Daily_Std": "0.968w"}}, "children": [], "ratio": 29.88898377, "_drillable": true}, {"name": "event_driven_202512", "kpi": {"kpi_2y": {"Net_Profit": "181.137w", "Max_Drawdown": "44.461w", "Ann_Sharpe": "1.643", "Daily_Std": "3.609w"}, "kpi_6m": {"Net_Profit": "24.279w", "Max_Drawdown": "44.461w", "Ann_Sharpe": "0.577", "Daily_Std": "5.548w"}}, "children": [], "ratio": 0.216841081, "_drillable": true}, {"name": "event_driven_202603", "kpi": {"kpi_2y": {"Net_Profit": "177.624w", "Max_Drawdown": "43.095w", "Ann_Sharpe": "2.087", "Daily_Std": "2.786w"}, "kpi_6m": {"Net_Profit": "40.282w", "Max_Drawdown": "43.095w", "Ann_Sharpe": "1.339", "Daily_Std": "3.963w"}}, "children": [], "ratio": 3.490401396, "_drillable": true}], "ratio": 92.0}