{"name": "tengfeng_500w_202512", "kpi": {"kpi_2y": {"Net_Profit": "426.679w", "Max_Drawdown": "39.521w", "Ann_Sharpe": "3.298", "Daily_Std": "4.253w"}, "kpi_6m": {"Net_Profit": "76.161w", "Max_Drawdown": "39.521w", "Ann_Sharpe": "2.131", "Daily_Std": "4.914w"}}, "children": [{"name": "all_weather_group_202512", "kpi": {"kpi_2y": {"Net_Profit": "307.769w", "Max_Drawdown": "36.168w", "Ann_Sharpe": "2.504", "Daily_Std": "4.041w"}, "kpi_6m": {"Net_Profit": "66.055w", "Max_Drawdown": "36.168w", "Ann_Sharpe": "1.937", "Daily_Std": "4.688w"}}, "children": [], "ratio": 42.14242823, "_drillable": true}, {"name": "sentiment_group_202511", "kpi": {"kpi_2y": {"Net_Profit": "314.595w", "Max_Drawdown": "19.829w", "Ann_Sharpe": "2.951", "Daily_Std": "3.504w"}, "kpi_6m": {"Net_Profit": "24.712w", "Max_Drawdown": "19.829w", "Ann_Sharpe": "1.311", "Daily_Std": "2.592w"}}, "children": [], "ratio": 13.81368821, "_drillable": true}, {"name": "volume_price_202511", "kpi": {"kpi_2y": {"Net_Profit": "321.359w", "Max_Drawdown": "30.797w", "Ann_Sharpe": "3.081", "Daily_Std": "3.429w"}, "kpi_6m": {"Net_Profit": "70.931w", "Max_Drawdown": "30.797w", "Ann_Sharpe": "2.511", "Daily_Std": "3.884w"}}, "children": [], "ratio": 8.06814875, "_drillable": true}, {"name": "multi_factor_202511", "kpi": {"kpi_2y": {"Net_Profit": "433.621w", "Max_Drawdown": "39.501w", "Ann_Sharpe": "2.913", "Daily_Std": "4.893w"}, "kpi_6m": {"Net_Profit": "84.381w", "Max_Drawdown": "15.299w", "Ann_Sharpe": "3.168", "Daily_Std": "3.662w"}}, "children": [], "ratio": 3.288648456, "_drillable": true}, {"name": "event_driven_202512", "kpi": {"kpi_2y": {"Net_Profit": "183.497w", "Max_Drawdown": "44.461w", "Ann_Sharpe": "1.669", "Daily_Std": "3.615w"}, "kpi_6m": {"Net_Profit": "20.653w", "Max_Drawdown": "44.461w", "Ann_Sharpe": "0.519", "Daily_Std": "5.468w"}}, "children": [], "ratio": 0.26348031, "_drillable": true}, {"name": "sentiment_group_202512", "kpi": {"kpi_2y": {"Net_Profit": "288.128w", "Max_Drawdown": "14.012w", "Ann_Sharpe": "3.238", "Daily_Std": "2.925w"}, "kpi_6m": {"Net_Profit": "52.797w", "Max_Drawdown": "14.012w", "Ann_Sharpe": "2.470", "Daily_Std": "2.939w"}}, "children": [], "ratio": 10.1888, "_drillable": true}, {"name": "multi_factor_202512", "kpi": {"kpi_2y": {"Net_Profit": "114.752w", "Max_Drawdown": "7.084w", "Ann_Sharpe": "3.477", "Daily_Std": "1.085w"}, "kpi_6m": {"Net_Profit": "19.038w", "Max_Drawdown": "5.773w", "Ann_Sharpe": "2.854", "Daily_Std": "0.917w"}}, "children": [], "ratio": 43.8888, "_drillable": true}, {"name": "volume_price_202601", "kpi": {"kpi_2y": {"Net_Profit": "323.728w", "Max_Drawdown": "31.539w", "Ann_Sharpe": "3.057", "Daily_Std": "3.481w"}, "kpi_6m": {"Net_Profit": "71.350w", "Max_Drawdown": "31.539w", "Ann_Sharpe": "2.441", "Daily_Std": "4.019w"}}, "children": [], "ratio": 8.16814875, "_drillable": true}, {"name": "all_weather_group_202601", "kpi": {"kpi_2y": {"Net_Profit": "294.527w", "Max_Drawdown": "37.910w", "Ann_Sharpe": "2.472", "Daily_Std": "3.916w"}, "kpi_6m": {"Net_Profit": "64.196w", "Max_Drawdown": "37.910w", "Ann_Sharpe": "1.858", "Daily_Std": "4.751w"}}, "children": [], "ratio": 32.884242823, "_drillable": true}, {"name": "event_driven_202601", "kpi": {"kpi_2y": {"Net_Profit": "160.708w", "Max_Drawdown": "40.487w", "Ann_Sharpe": "1.972", "Daily_Std": "2.679w"}, "kpi_6m": {"Net_Profit": "28.489w", "Max_Drawdown": "40.487w", "Ann_Sharpe": "1.058", "Daily_Std": "3.701w"}}, "children": [], "ratio": 5.86348031, "_drillable": true}], "ratio": 28.0}