{"name": "AutoCTA_short_index_202503", "kpi": {"kpi_2y": {"Net_Profit": "81.576w", "Max_Drawdown": "7.224w", "Ann_Sharpe": "2.827", "Daily_Std": "0.950w"}, "kpi_6m": {"Net_Profit": "25.538w", "Max_Drawdown": "4.627w", "Ann_Sharpe": "3.440", "Daily_Std": "1.039w"}}, "children": [{"name": "RawSigSS-IterBKT-SS2223", "kpi": {"kpi_2y": {"Net_Profit": "14.710w", "Max_Drawdown": "2.230w", "Ann_Sharpe": "1.658", "Daily_Std": "0.292w"}, "kpi_6m": {"Net_Profit": "8.403w", "Max_Drawdown": "1.189w", "Ann_Sharpe": "3.658", "Daily_Std": "0.321w"}}, "children": [], "ratio": 56.42}, {"name": "RawSigSSRY_IterBKT_SS2024", "kpi": {"kpi_2y": {"Net_Profit": "67.946w", "Max_Drawdown": "7.709w", "Ann_Sharpe": "2.199", "Daily_Std": "1.018w"}, "kpi_6m": {"Net_Profit": "10.220w", "Max_Drawdown": "3.718w", "Ann_Sharpe": "1.871", "Daily_Std": "0.764w"}}, "children": [], "ratio": 21.95}, {"name": "RawSigSS_IterBKT_SS202409", "kpi": {"kpi_2y": {"Net_Profit": "48.491w", "Max_Drawdown": "3.914w", "Ann_Sharpe": "2.921", "Daily_Std": "0.547w"}, "kpi_6m": {"Net_Profit": "13.705w", "Max_Drawdown": "2.562w", "Ann_Sharpe": "3.205", "Daily_Std": "0.598w"}}, "children": [], "ratio": 77.13}, {"name": "RawSigSS_IterBKT_SS202409_SelectTop", "kpi": {"kpi_2y": {"Net_Profit": "56.315w", "Max_Drawdown": "5.469w", "Ann_Sharpe": "2.643", "Daily_Std": "0.702w"}, "kpi_6m": {"Net_Profit": "22.406w", "Max_Drawdown": "3.237w", "Ann_Sharpe": "3.608", "Daily_Std": "0.869w"}}, "children": [], "ratio": 29.57}, {"name": "RawSigSS_IterBKT_SS202409_VBigTpBigpTwp", "kpi": {"kpi_2y": {"Net_Profit": "36.080w", "Max_Drawdown": "4.684w", "Ann_Sharpe": "2.321", "Daily_Std": "0.512w"}, "kpi_6m": {"Net_Profit": "8.170w", "Max_Drawdown": "4.319w", "Ann_Sharpe": "2.240", "Daily_Std": "0.510w"}}, "children": [], "ratio": 17.4}], "ratio": 100.0}