{"name": "FuxingGroup_202601", "kpi": {"kpi_2y": {"Net_Profit": "111.954w", "Max_Drawdown": "4.571w", "Ann_Sharpe": "4.751", "Daily_Std": "0.773w"}, "kpi_6m": {"Net_Profit": "24.351w", "Max_Drawdown": "4.571w", "Ann_Sharpe": "3.864", "Daily_Std": "0.882w"}}, "children": [{"name": "FM_202601", "kpi": {"kpi_2y": {"Net_Profit": "110.795w", "Max_Drawdown": "6.192w", "Ann_Sharpe": "3.872", "Daily_Std": "0.939w"}, "kpi_6m": {"Net_Profit": "22.199w", "Max_Drawdown": "4.972w", "Ann_Sharpe": "3.349", "Daily_Std": "0.928w"}}, "children": [], "ratio": 42.697994858148405, "_drillable": true}, {"name": "CTA_202503II", "kpi": {"kpi_2y": {"Net_Profit": "95.704w", "Max_Drawdown": "4.187w", "Ann_Sharpe": "4.058", "Daily_Std": "0.774w"}, "kpi_6m": {"Net_Profit": "24.819w", "Max_Drawdown": "4.187w", "Ann_Sharpe": "3.870", "Daily_Std": "0.897w"}}, "children": [], "ratio": 41.42790091418363, "_drillable": true}, {"name": "tengfeng_1000w", "kpi": {"kpi_2y": {"Net_Profit": "567.028w", "Max_Drawdown": "44.413w", "Ann_Sharpe": "3.179", "Daily_Std": "5.851w"}, "kpi_6m": {"Net_Profit": "110.308w", "Max_Drawdown": "43.401w", "Ann_Sharpe": "2.277", "Daily_Std": "6.778w"}}, "children": [], "ratio": 1.4998965185830808, "_drillable": true}, {"name": "minblock_sif_vp_202507", "kpi": {"kpi_2y": {"Net_Profit": "58.359w", "Max_Drawdown": "15.917w", "Ann_Sharpe": "1.904", "Daily_Std": "1.005w"}, "kpi_6m": {"Net_Profit": "3.533w", "Max_Drawdown": "14.142w", "Ann_Sharpe": "0.347", "Daily_Std": "1.423w"}}, "children": [], "ratio": 8.175025487609625}, {"name": "minblock_ttf_202501", "kpi": {"kpi_2y": {"Net_Profit": "18.946w", "Max_Drawdown": "24.286w", "Ann_Sharpe": "0.644", "Daily_Std": "0.965w"}, "kpi_6m": {"Net_Profit": "-10.819w", "Max_Drawdown": "11.923w", "Ann_Sharpe": "-2.191", "Daily_Std": "0.691w"}}, "children": [], "ratio": 1.871354373147577}, {"name": "ifp_complex_group", "kpi": {"kpi_2y": {"Net_Profit": "152.420w", "Max_Drawdown": "8.321w", "Ann_Sharpe": "3.965", "Daily_Std": "1.261w"}, "kpi_6m": {"Net_Profit": "32.406w", "Max_Drawdown": "5.538w", "Ann_Sharpe": "3.458", "Daily_Std": "1.311w"}}, "children": [], "ratio": 3.141, "_drillable": true}], "ratio": 3000.0}