{"name": "MLP_Group_20250518", "kpi": {"kpi_2y": {"Net_Profit": "100.115w", "Max_Drawdown": "22.972w", "Ann_Sharpe": "1.820", "Daily_Std": "1.800w"}, "kpi_6m": {"Net_Profit": "6.451w", "Max_Drawdown": "10.750w", "Ann_Sharpe": "0.668", "Daily_Std": "1.306w"}}, "children": [{"name": "MLP_State_Predict_LongShort", "kpi": {"kpi_2y": {"Net_Profit": "105.596w", "Max_Drawdown": "32.170w", "Ann_Sharpe": "1.446", "Daily_Std": "2.390w"}, "kpi_6m": {"Net_Profit": "-8.039w", "Max_Drawdown": "29.032w", "Ann_Sharpe": "-0.566", "Daily_Std": "1.920w"}}, "children": [], "ratio": 17.39130435}, {"name": "MLP_State_Predict_LongOnly", "kpi": {"kpi_2y": {"Net_Profit": "132.056w", "Max_Drawdown": "19.527w", "Ann_Sharpe": "1.954", "Daily_Std": "2.213w"}, "kpi_6m": {"Net_Profit": "20.922w", "Max_Drawdown": "19.527w", "Ann_Sharpe": "1.516", "Daily_Std": "1.865w"}}, "children": [], "ratio": 18.40773125}, {"name": "MLP_State_Predict_LongOnly_Smoth", "kpi": {"kpi_2y": {"Net_Profit": "109.347w", "Max_Drawdown": "16.804w", "Ann_Sharpe": "1.887", "Daily_Std": "1.897w"}, "kpi_6m": {"Net_Profit": "23.048w", "Max_Drawdown": "16.804w", "Ann_Sharpe": "1.757", "Daily_Std": "1.773w"}}, "children": [], "ratio": 21.5866163}, {"name": "MLP_State_Predict_UseProbability", "kpi": {"kpi_2y": {"Net_Profit": "192.185w", "Max_Drawdown": "108.518w", "Ann_Sharpe": "1.328", "Daily_Std": "4.738w"}, "kpi_6m": {"Net_Profit": "-8.314w", "Max_Drawdown": "43.150w", "Ann_Sharpe": "-0.310", "Daily_Std": "3.620w"}}, "children": [], "ratio": 8.729812309}, {"name": "MLP_State_Predict_UseProbability_Smoth", "kpi": {"kpi_2y": {"Net_Profit": "123.497w", "Max_Drawdown": "60.380w", "Ann_Sharpe": "1.290", "Daily_Std": "3.133w"}, "kpi_6m": {"Net_Profit": "-8.620w", "Max_Drawdown": "29.654w", "Ann_Sharpe": "-0.553", "Daily_Std": "2.108w"}}, "children": [], "ratio": 12.68633048}], "ratio": 0.569513678}