{"name": "pyelf_21ENetLong_newfilter_tp50_group4_2025wf", "kpi": {"kpi_2y": {"Net_Profit": "275.252w", "Max_Drawdown": "101.507w", "Ann_Sharpe": "1.377", "Daily_Std": "6.556w"}, "kpi_6m": {"Net_Profit": "31.558w", "Max_Drawdown": "56.775w", "Ann_Sharpe": "0.594", "Daily_Std": "7.438w"}}, "children": [{"name": "pyelf_21ENetlong_adx_tp50_day_2025wf", "kpi": {"kpi_2y": {"Net_Profit": "260.479w", "Max_Drawdown": "39.620w", "Ann_Sharpe": "2.152", "Daily_Std": "3.970w"}, "kpi_6m": {"Net_Profit": "13.755w", "Max_Drawdown": "39.620w", "Ann_Sharpe": "0.486", "Daily_Std": "3.958w"}}, "children": [], "ratio": 25.89}, {"name": "pyelf_21ENetLong_onlytrend_tp50_day_2025wf", "kpi": {"kpi_2y": {"Net_Profit": "202.420w", "Max_Drawdown": "56.416w", "Ann_Sharpe": "1.180", "Daily_Std": "5.628w"}, "kpi_6m": {"Net_Profit": "78.998w", "Max_Drawdown": "51.959w", "Ann_Sharpe": "1.387", "Daily_Std": "7.970w"}}, "children": [], "ratio": 20.63}, {"name": "pyelf_21ENetlong_onlyyzvol_tp50_day_2025wf", "kpi": {"kpi_2y": {"Net_Profit": "467.011w", "Max_Drawdown": "301.217w", "Ann_Sharpe": "0.943", "Daily_Std": "16.254w"}, "kpi_6m": {"Net_Profit": "-25.302w", "Max_Drawdown": "195.494w", "Ann_Sharpe": "-0.203", "Daily_Std": "17.434w"}}, "children": [], "ratio": 15.6, "_drillable": true}, {"name": "pyelf_21ENetlong_pricepos_tp50_day_2025wf", "kpi": {"kpi_2y": {"Net_Profit": "240.607w", "Max_Drawdown": "42.570w", "Ann_Sharpe": "1.676", "Daily_Std": "4.709w"}, "kpi_6m": {"Net_Profit": "66.409w", "Max_Drawdown": "42.570w", "Ann_Sharpe": "1.712", "Daily_Std": "5.426w"}}, "children": [], "ratio": 19.11, "_drillable": true}, {"name": "pyelf_21ENetlong_onlytrendsingle_tp50_day_2025wf", "kpi": {"kpi_2y": {"Net_Profit": "304.126w", "Max_Drawdown": "182.854w", "Ann_Sharpe": "1.181", "Daily_Std": "8.448w"}, "kpi_6m": {"Net_Profit": "70.100w", "Max_Drawdown": "78.661w", "Ann_Sharpe": "0.997", "Daily_Std": "9.840w"}}, "children": [], "ratio": 18.77, "_drillable": true}], "ratio": 1.691}