{"name": "pyelf_21ENetLong_onlygapintraday_tp50_day_2025wf", "kpi": {"kpi_2y": {"Net_Profit": "245.756w", "Max_Drawdown": "55.429w", "Ann_Sharpe": "1.378", "Daily_Std": "5.851w"}, "kpi_6m": {"Net_Profit": "102.090w", "Max_Drawdown": "49.424w", "Ann_Sharpe": "2.072", "Daily_Std": "6.775w"}}, "children": [{"name": "pyelf_21ENet5MDiffYP3_onlygapintraday_tp50_day_2025wf", "kpi": {"kpi_2y": {"Net_Profit": "248.864w", "Max_Drawdown": "55.831w", "Ann_Sharpe": "1.365", "Daily_Std": "5.979w"}, "kpi_6m": {"Net_Profit": "92.080w", "Max_Drawdown": "42.233w", "Ann_Sharpe": "1.986", "Daily_Std": "6.373w"}}, "children": [], "ratio": 33.0}, {"name": "pyelf_21ENet5MDiffYP5_onlygapintraday_tp50_day_2025wf", "kpi": {"kpi_2y": {"Net_Profit": "256.163w", "Max_Drawdown": "55.449w", "Ann_Sharpe": "1.413", "Daily_Std": "5.946w"}, "kpi_6m": {"Net_Profit": "102.632w", "Max_Drawdown": "55.449w", "Ann_Sharpe": "2.002", "Daily_Std": "7.047w"}}, "children": [], "ratio": 34.0}, {"name": "pyelf_21ENet6MDiffYP5_onlygapintraday_tp50_day_2025wf", "kpi": {"kpi_2y": {"Net_Profit": "234.151w", "Max_Drawdown": "59.596w", "Ann_Sharpe": "1.326", "Daily_Std": "5.792w"}, "kpi_6m": {"Net_Profit": "114.191w", "Max_Drawdown": "50.406w", "Ann_Sharpe": "2.219", "Daily_Std": "7.075w"}}, "children": [], "ratio": 33.0}], "ratio": 43.8}