{"name": "tengfeng_500w_202603", "kpi": {"kpi_2y": {"Net_Profit": "381.810w", "Max_Drawdown": "30.170w", "Ann_Sharpe": "3.408", "Daily_Std": "3.683w"}, "kpi_6m": {"Net_Profit": "78.882w", "Max_Drawdown": "30.170w", "Ann_Sharpe": "2.496", "Daily_Std": "4.235w"}}, "children": [{"name": "all_weather_group_202512", "kpi": {"kpi_2y": {"Net_Profit": "296.303w", "Max_Drawdown": "36.168w", "Ann_Sharpe": "2.409", "Daily_Std": "4.043w"}, "kpi_6m": {"Net_Profit": "57.400w", "Max_Drawdown": "36.168w", "Ann_Sharpe": "1.647", "Daily_Std": "4.671w"}}, "children": [], "ratio": 25.9495164, "_drillable": true}, {"name": "all_weather_group_202603", "kpi": {"kpi_2y": {"Net_Profit": "243.935w", "Max_Drawdown": "31.653w", "Ann_Sharpe": "2.309", "Daily_Std": "3.472w"}, "kpi_6m": {"Net_Profit": "51.542w", "Max_Drawdown": "30.517w", "Ann_Sharpe": "1.786", "Daily_Std": "3.867w"}}, "children": [], "ratio": 33.18019398, "_drillable": true}, {"name": "sentiment_group_202511", "kpi": {"kpi_2y": {"Net_Profit": "310.211w", "Max_Drawdown": "19.829w", "Ann_Sharpe": "2.904", "Daily_Std": "3.512w"}, "kpi_6m": {"Net_Profit": "26.647w", "Max_Drawdown": "19.829w", "Ann_Sharpe": "1.263", "Daily_Std": "2.827w"}}, "children": [], "ratio": 9.458948165, "_drillable": true}, {"name": "sentiment_group_202512", "kpi": {"kpi_2y": {"Net_Profit": "277.685w", "Max_Drawdown": "14.012w", "Ann_Sharpe": "3.094", "Daily_Std": "2.951w"}, "kpi_6m": {"Net_Profit": "52.851w", "Max_Drawdown": "14.012w", "Ann_Sharpe": "2.291", "Daily_Std": "3.092w"}}, "children": [], "ratio": 21.73125679, "_drillable": true}, {"name": "volume_price_202511", "kpi": {"kpi_2y": {"Net_Profit": "309.605w", "Max_Drawdown": "30.797w", "Ann_Sharpe": "2.954", "Daily_Std": "3.446w"}, "kpi_6m": {"Net_Profit": "54.272w", "Max_Drawdown": "30.797w", "Ann_Sharpe": "1.774", "Daily_Std": "4.098w"}}, "children": [], "ratio": 3.825554705, "_drillable": true}, {"name": "volume_price_202601", "kpi": {"kpi_2y": {"Net_Profit": "311.521w", "Max_Drawdown": "31.539w", "Ann_Sharpe": "2.926", "Daily_Std": "3.499w"}, "kpi_6m": {"Net_Profit": "56.795w", "Max_Drawdown": "31.539w", "Ann_Sharpe": "1.819", "Daily_Std": "4.185w"}}, "children": [], "ratio": 3.785966683, "_drillable": true}, {"name": "volume_price_202603", "kpi": {"kpi_2y": {"Net_Profit": "307.760w", "Max_Drawdown": "22.377w", "Ann_Sharpe": "3.161", "Daily_Std": "3.200w"}, "kpi_6m": {"Net_Profit": "82.203w", "Max_Drawdown": "22.377w", "Ann_Sharpe": "2.665", "Daily_Std": "4.133w"}}, "children": [], "ratio": 16.41586867, "_drillable": true}, {"name": "multi_factor_202511", "kpi": {"kpi_2y": {"Net_Profit": "424.207w", "Max_Drawdown": "39.501w", "Ann_Sharpe": "2.834", "Daily_Std": "4.920w"}, "kpi_6m": {"Net_Profit": "101.095w", "Max_Drawdown": "15.299w", "Ann_Sharpe": "3.454", "Daily_Std": "3.922w"}}, "children": [], "ratio": 7.163323782, "_drillable": true}, {"name": "multi_factor_202512", "kpi": {"kpi_2y": {"Net_Profit": "115.732w", "Max_Drawdown": "7.084w", "Ann_Sharpe": "3.472", "Daily_Std": "1.096w"}, "kpi_6m": {"Net_Profit": "20.745w", "Max_Drawdown": "5.773w", "Ann_Sharpe": "2.830", "Daily_Std": "0.982w"}}, "children": [], "ratio": 29.88898377, "_drillable": true}, {"name": "event_driven_202512", "kpi": {"kpi_2y": {"Net_Profit": "180.396w", "Max_Drawdown": "44.461w", "Ann_Sharpe": "1.641", "Daily_Std": "3.614w"}, "kpi_6m": {"Net_Profit": "28.525w", "Max_Drawdown": "44.461w", "Ann_Sharpe": "0.676", "Daily_Std": "5.653w"}}, "children": [], "ratio": 0.216841081, "_drillable": true}, {"name": "event_driven_202603", "kpi": {"kpi_2y": {"Net_Profit": "172.994w", "Max_Drawdown": "43.095w", "Ann_Sharpe": "2.042", "Daily_Std": "2.785w"}, "kpi_6m": {"Net_Profit": "34.608w", "Max_Drawdown": "43.095w", "Ann_Sharpe": "1.166", "Daily_Std": "3.978w"}}, "children": [], "ratio": 3.490401396, "_drillable": true}], "ratio": 82.0}